pymcel/__init__.py
pymcel/constantes.py
pymcel/export.py
pymcel/extra.py
pymcel/plot.py
pymcel/version.py
pymcel/data/JupiterComets.csv
pymcel/data/NEOs.csv
pymcel/data/de430.tpc
pymcel/data/kernels
pymcel/data/kernels.txt
pymcel-0.6.31.dist-info/licenses/LICENSE
pymcel-0.6.31.dist-info/METADATA
pymcel-0.6.31.dist-info/WHEEL
pymcel-0.6.31.dist-info/entry_points.txt
pymcel-0.6.31.dist-info/top_level.txt
pymcel-0.6.31.dist-info/RECORD
