Metadata-Version: 2.4
Name: pymcel
Version: 0.6.31
Summary: Utilidades de Mecánica Celeste
Home-page: https://pypi.org/project/pymcel
Author: Jorge I. Zuluaga
Author-email: jorge.zuluaga@udea.edu.co
License: MIT
Keywords: astronomy astrodynamics
Classifier: Programming Language :: Python :: 3
Classifier: License :: OSI Approved :: MIT License
Classifier: Operating System :: OS Independent
License-File: LICENSE
Requires-Dist: spiceypy
Requires-Dist: astroquery
Requires-Dist: pandas
Requires-Dist: matplotlib
Requires-Dist: tqdm
Requires-Dist: pandas
Requires-Dist: plotly
Dynamic: author
Dynamic: author-email
Dynamic: classifier
Dynamic: description
Dynamic: description-content-type
Dynamic: home-page
Dynamic: keywords
Dynamic: license
Dynamic: license-file
Dynamic: requires-dist
Dynamic: summary
